setup.py
django_FIUT.egg-info/PKG-INFO
django_FIUT.egg-info/SOURCES.txt
django_FIUT.egg-info/dependency_links.txt
django_FIUT.egg-info/top_level.txt
fiut/__init__.py
fiut/context_processors.py
fiut/forms.py
fiut/helpers.py
fiut/models.py