Metadata-Version: 1.1
Name: django-FIUT
Version: 0.1.7
Summary: Fine, Incredibly Useful Tools
Home-page: https://github.com/v0y/django-FIUT
Author: Rafal Mironczyk
Author-email: voyageur.pl@gmail.com
License: MIT
Platform: UNKNOWN
Classifier: Environment :: Web Environment
Classifier: Intended Audience :: Developers
Classifier: Operating System :: OS Independent
Classifier: Programming Language :: Python
Classifier: Programming Language :: Python :: 3
Classifier: Framework :: Django
